{
  "component": {
    "stack": {
      "even-less": {
        "value": {
          "itemSpacing": "{dimension.least}"
        },
        "type": "composition"
      },
      "less": {
        "value": {
          "itemSpacing": "{dimension.even-less}"
        },
        "type": "composition"
      },
      "bit-less": {
        "value": {
          "itemSpacing": "{dimension.less}"
        },
        "type": "composition"
      },
      "default": {
        "value": {
          "itemSpacing": "{dimension.bit-less}",
          "width": "({screen.width} - ({grid.gutter}*4)) / 3"
        },
        "type": "composition"
      },
      "bit-more": {
        "value": {
          "itemSpacing": "{dimension.default}"
        },
        "type": "composition"
      },
      "more": {
        "value": {
          "itemSpacing": "{dimension.bit-more}"
        },
        "type": "composition"
      },
      "even-more": {
        "value": {
          "itemSpacing": "{dimension.more}"
        },
        "type": "composition"
      }
    },
    "inline": {
      "even-less": {
        "value": {
          "itemSpacing": "{dimension.least}"
        },
        "type": "composition"
      },
      "less": {
        "value": {
          "itemSpacing": "{dimension.even-less}"
        },
        "type": "composition"
      },
      "bit-less": {
        "value": {
          "itemSpacing": "{dimension.less}"
        },
        "type": "composition"
      },
      "default": {
        "value": {
          "itemSpacing": "{dimension.bit-less}"
        },
        "type": "composition"
      },
      "bit-more": {
        "value": {
          "itemSpacing": "{dimension.default}"
        },
        "type": "composition"
      },
      "more": {
        "value": {
          "itemSpacing": "{dimension.bit-more}"
        },
        "type": "composition"
      },
      "even-more": {
        "value": {
          "itemSpacing": "{dimension.more}"
        },
        "type": "composition"
      }
    }
  },
  "layout": {
    "stack": {
      "even-less": {
        "value": {
          "itemSpacing": "{dimension.less}"
        },
        "type": "composition"
      },
      "less": {
        "value": {
          "itemSpacing": "{dimension.bit-less}"
        },
        "type": "composition"
      },
      "bit-less": {
        "value": {
          "itemSpacing": "{dimension.default}"
        },
        "type": "composition"
      },
      "default": {
        "value": {
          "itemSpacing": "{dimension.bit-more}"
        },
        "type": "composition"
      },
      "bit-more": {
        "value": {
          "itemSpacing": "{dimension.more}"
        },
        "type": "composition"
      },
      "more": {
        "value": {
          "itemSpacing": "{dimension.even-more}"
        },
        "type": "composition"
      },
      "even-more": {
        "value": {
          "itemSpacing": "{dimension.most}"
        },
        "type": "composition"
      }
    },
    "inline": {
      "even-less": {
        "value": {
          "itemSpacing": "{dimension.less}"
        },
        "type": "composition"
      },
      "less": {
        "value": {
          "itemSpacing": "{dimension.bit-less}"
        },
        "type": "composition"
      },
      "bit-less": {
        "value": {
          "itemSpacing": "{dimension.default}"
        },
        "type": "composition"
      },
      "default": {
        "value": {
          "itemSpacing": "{dimension.bit-more}"
        },
        "type": "composition"
      },
      "bit-more": {
        "value": {
          "itemSpacing": "{dimension.more}"
        },
        "type": "composition"
      },
      "more": {
        "value": {
          "itemSpacing": "{dimension.even-more}"
        },
        "type": "composition"
      },
      "even-more": {
        "value": {
          "itemSpacing": "{dimension.most}"
        },
        "type": "composition"
      }
    }
  }
}